[
  {
    "n": "0",
    "registro": "0 de 25",
    "ordem_exibicao": 1,
    "idioma_01": "POR",
    "idioma_02": "",
    "vocabulario_controlado": "CAPA",
    "titulo_artigo": "O fim das vanguardas como elas eram",
    "subtitulo_artigo": "",
    "paginas": "p.1",
    "resumo": "",
    "nota_edicao": "",
    "autores_colaboradores": [],
    "tradutores": [],
    "autores_citados": [],
    "palavras_chave": [],
    "nome_pessoal_como_assunto": [],
    "iconografias": [
      {
        "tipo": "Foto",
        "descricao": "\"Along Pico Looking North\", (fotografia colorida), FLICK, Robert, s/d"
      }
    ],
    "_timestamp": "2025-11-23T21:31:41.379084",
    "_id": "1763944301379",
    "notas_pesquisa": []
  },
  {
    "n": "0",
    "registro": "1 de 25",
    "ordem_exibicao": 2,
    "idioma_01": "POR",
    "idioma_02": "",
    "vocabulario_controlado": "EDITORIAL",
    "titulo_artigo": "Editorial",
    "subtitulo_artigo": "",
    "paginas": "p.6-7",
    "resumo": "Editorial programático que apresenta a concepção de linguagem, arte e crítica que orienta a revista Sibila. A partir de uma referência inicial a Drummond, formula-se a imagem dos poemas como palavras em estado de dicionário, à espera de quem as faça passar ao improvável, indicando que os melhores dicionários são os próprios poemas, nos quais as palavras permanecem simultaneamente neutras e desafiadoras. Defende-se que não há novidade sem história e que toda revolução supõe retorno a um ponto ainda intocado. O texto explicita que essa postura de provocação não agressiva, própria da arte, será também diretriz da crítica na revista, que assume ainda o risco do erro. Justifica-se a escolha do nome “Sibila”, extraído do poema “Grafito para Giuseppe Capogrossi”, de Murilo Mendes, destacando sua dimensão metalinguística, o questionamento da representação, o lirismo anti-lírico e a ilegibilidade, aproximados de aspectos da poesia contemporânea. A figura da Sibila é retomada como enigma e profecia, em diálogo com Aristóteles, para pensar a revista como mensagem instável projetada para o futuro, mas atenta ao passado como repertório de interrogações. Afirmam-se, por fim, o compromisso com a diferença como condição de identidade, a abertura a outros países e línguas e a visão da arte como poder transformador e da literatura como pensamento autocriticamente vigilante.",
    "nota_edicao": "",
    "autores_colaboradores": [],
    "entidade_coletiva": [
      "SIBILA"
    ],
    "tradutores": [],
    "autores_citados": [
      "DRUMMOND, Drummond",
      "MENDES, Murilo",
      "CAPOGROSSI, Giuseppe",
      "ARISTÓTELES, Aristóteles"
    ],
    "palavras_chave": [
      "Literatura",
      "Poesia",
      "Arte",
      "Cultura",
      "Identidade"
    ],
    "nome_pessoal_como_assunto": [],
    "iconografias": [
      {
        "tipo": "Ilustração",
        "descricao": ""
      }
    ],
    "_timestamp": "2025-11-23T21:49:23.579317",
    "_id": "1763945363579",
    "notas_pesquisa": []
  },
  {
    "n": "0",
    "registro": "2 de 25",
    "ordem_exibicao": 3,
    "idioma_01": "POR",
    "idioma_02": "",
    "vocabulario_controlado": "POEMA(S)",
    "titulo_artigo": "Grafito para Giuseppe Capogrossi",
    "subtitulo_artigo": "",
    "paginas": "p.8-9",
    "resumo": "",
    "nota_edicao": "",
    "autores_colaboradores": [
      "MENDES, Murilo"
    ],
    "entidade_coletiva": [],
    "tradutores": [],
    "autores_citados": [],
    "palavras_chave": [],
    "nome_pessoal_como_assunto": [],
    "iconografias": [
      {
        "tipo": "Reprodução",
        "descricao": "s/título, s/crédito, s/d, p. 8"
      }
    ],
    "_timestamp": "2025-11-23T23:46:13.340844",
    "_id": "1763952373340",
    "notas_pesquisa": []
  },
  {
    "n": "0",
    "registro": "3 de 25",
    "ordem_exibicao": 4,
    "idioma_01": "ING",
    "idioma_02": "POR",
    "vocabulario_controlado": "POEMA(S)",
    "titulo_artigo": "De parsing",
    "subtitulo_artigo": "",
    "paginas": "p.10-13",
    "resumo": "[Publicação bilíngue]",
    "nota_edicao": "",
    "autores_colaboradores": [
      "BERNSTEIN, Charles"
    ],
    "entidade_coletiva": [],
    "tradutores": [
      "BONVICINO, Regis"
    ],
    "autores_citados": [],
    "palavras_chave": [],
    "nome_pessoal_como_assunto": [],
    "iconografias": [],
    "_timestamp": "2025-11-24T00:08:52.487629",
    "notas_pesquisa": [],
    "_id": "1763953327417"
  },
  {
    "n": "0",
    "registro": "4 de 25",
    "ordem_exibicao": 5,
    "idioma_01": "POR",
    "idioma_02": "ING",
    "vocabulario_controlado": "POEMA(S)",
    "titulo_artigo": "Poema (de caprichos e relaxos)",
    "subtitulo_artigo": "",
    "paginas": "p.14-15",
    "resumo": "[Publicação bilíngue]",
    "nota_edicao": "",
    "autores_colaboradores": [
      "LEMINSKI, Paulo"
    ],
    "entidade_coletiva": [],
    "tradutores": [
      "BERNSTEIN, Charles",
      "BONVICINO, Regis"
    ],
    "autores_citados": [],
    "palavras_chave": [],
    "nome_pessoal_como_assunto": [],
    "iconografias": [],
    "_timestamp": "2025-11-24T00:03:10.339793",
    "_id": "1763953390339",
    "notas_pesquisa": []
  },
  {
    "n": "0",
    "registro": "5 de 25",
    "ordem_exibicao": 6,
    "idioma_01": "ING",
    "idioma_02": "POR",
    "vocabulario_controlado": "POEMA(S)",
    "titulo_artigo": "Estar for Hélio Oiticica",
    "subtitulo_artigo": "",
    "paginas": "p.16-17",
    "resumo": "[Publicação bilíngue]",
    "nota_edicao": "",
    "autores_colaboradores": [
      "COLE, Norma"
    ],
    "entidade_coletiva": [],
    "tradutores": [
      "TEIXEIRA, Virna G."
    ],
    "autores_citados": [],
    "palavras_chave": [],
    "nome_pessoal_como_assunto": [],
    "iconografias": [],
    "_timestamp": "2025-11-24T00:26:31.529581",
    "_id": "1763954791529",
    "notas_pesquisa": []
  },
  {
    "n": "0",
    "registro": "6 de 25",
    "ordem_exibicao": 7,
    "idioma_01": "FRA",
    "idioma_02": "POR",
    "vocabulario_controlado": "POEMA(S)",
    "titulo_artigo": "Poemas",
    "subtitulo_artigo": "",
    "paginas": "p.18-21",
    "resumo": "Textos de \"Poèmes\". As versões em inglês são de Samuel Beckett, as traduções em português são de Júlio Castañon Guimarães. [Publicação bilíngue.]",
    "nota_edicao": "",
    "autores_colaboradores": [
      "BECKETT, Samuel"
    ],
    "entidade_coletiva": [],
    "tradutores": [
      "BECKETT, Samuel",
      "GUIMARÃES, Júlio Castañon"
    ],
    "autores_citados": [],
    "palavras_chave": [],
    "nome_pessoal_como_assunto": [],
    "iconografias": [],
    "_timestamp": "2025-11-24T00:39:21.442787",
    "_id": "1763955561442",
    "notas_pesquisa": []
  },
  {
    "n": "0",
    "registro": "7 de 25",
    "ordem_exibicao": 8,
    "idioma_01": "ESP",
    "idioma_02": "",
    "vocabulario_controlado": "POEMA(S)",
    "titulo_artigo": "Concierto de cello",
    "subtitulo_artigo": "",
    "paginas": "p.22-23",
    "resumo": "",
    "nota_edicao": "",
    "autores_colaboradores": [
      "ULACIA, Manuel"
    ],
    "entidade_coletiva": [],
    "tradutores": [],
    "autores_citados": [],
    "palavras_chave": [],
    "nome_pessoal_como_assunto": [],
    "iconografias": [],
    "_timestamp": "2025-11-24T00:45:03.587989",
    "_id": "1763955903588",
    "notas_pesquisa": []
  }
]